airobo/__init__.py
airobo/api.py
airobo/cli.py
airobo/modules/capacitorMacro.py
airobo/modules/getLatestAppSource.py
airobo/modules/android/buildAndroid.py
airobo/modules/android/publishAndroid.py
airobo/modules/ios/publishIOS.py
airobo/utils/env.py
airobo-0.1.93.dist-info/METADATA
airobo-0.1.93.dist-info/WHEEL
airobo-0.1.93.dist-info/entry_points.txt
airobo-0.1.93.dist-info/top_level.txt
airobo-0.1.93.dist-info/RECORD
