Metadata-Version: 2.4
Name: airobo
Version: 0.1.93
Summary: A CLI tool for Airobo tasks
Author-email: Joshua Morvant <joshua@aiarobo.com>
Requires-Python: >=3.7
